electoral_system_analysis/__init__.py
electoral_system_analysis/clean_electoral_data.py
electoral_system_analysis/distribution_formulas.py
electoral_system_analysis/distribution_regions.py
tests/__init__.py
tests/test_distribution_formulas.py
tests/test_distribution_regions.py
electoral_system_analysis-1.0.2.dist-info/LICENSE
electoral_system_analysis-1.0.2.dist-info/METADATA
electoral_system_analysis-1.0.2.dist-info/WHEEL
electoral_system_analysis-1.0.2.dist-info/top_level.txt
electoral_system_analysis-1.0.2.dist-info/RECORD
