Metadata-Version: 2.1
Name: electoral-system-analysis
Version: 1.0.2
Summary: Repositorio que recoge diferentes elementos de sistemas electorales para su comparación, dentro de los marcos de la constitución española de 1978.
Home-page: https://github.com/santhiperbolico/analisis-de-sistemas-electorales
Author: Santiago Arranz Sanz
Classifier: Programming Language :: Python :: 3
Classifier: License :: OSI Approved :: MIT License
Classifier: Operating System :: OS Independent
Requires-Python: >=3.8
License-File: LICENSE
Requires-Dist: pandas
